{
  "vite/modulepreload-polyfill": [],
  "locales/ar.yml": [],
  "locales/de.yml": [],
  "locales/en.yml": [],
  "locales/es.yml": [],
  "locales/fr.yml": [],
  "locales/id.yml": [],
  "locales/it.yml": [],
  "locales/ja.yml": [],
  "locales/ko.yml": [],
  "locales/pl.yml": [],
  "locales/pt-BR.yml": [],
  "locales/ru.yml": [],
  "locales/tr.yml": [],
  "locales/uk.yml": [],
  "locales/vi.yml": [],
  "locales/zh-CN.yml": [],
  "node_modules/.pnpm/@intlify+shared@9.2.2/node_modules/@intlify/shared/dist/shared.esm-bundler.js": [],
  "node_modules/.pnpm/@intlify+message-compiler@9.2.2/node_modules/@intlify/message-compiler/dist/message-compiler.esm-bundler.js": [],
  "node_modules/.pnpm/@intlify+devtools-if@9.2.2/node_modules/@intlify/devtools-if/dist/devtools-if.esm-bundler.js": [],
  "node_modules/.pnpm/@intlify+core-base@9.2.2/node_modules/@intlify/core-base/dist/core-base.esm-bundler.js": [],
  "node_modules/.pnpm/@vue+shared@3.2.45/node_modules/@vue/shared/dist/shared.esm-bundler.js": [],
  "node_modules/.pnpm/@vue+reactivity@3.2.45/node_modules/@vue/reactivity/dist/reactivity.esm-bundler.js": [],
  "node_modules/.pnpm/@vue+runtime-core@3.2.45/node_modules/@vue/runtime-core/dist/runtime-core.esm-bundler.js": [],
  "node_modules/.pnpm/@vue+runtime-dom@3.2.45/node_modules/@vue/runtime-dom/dist/runtime-dom.esm-bundler.js": [],
  "node_modules/.pnpm/vue-i18n@9.2.2_vue@3.2.45/node_modules/vue-i18n/dist/vue-i18n.runtime.esm-bundler.js": [],
  "src/modules/i18n.ts": [],
  "\u0000commonjsHelpers.js": [],
  "\u0000C:/Users/arbus/Documents/Gatobuho/[TomosYTumbas]/tyt-ruleset/node_modules/.pnpm/nprogress@0.2.0/node_modules/nprogress/nprogress.js?commonjs-module": [],
  "node_modules/.pnpm/nprogress@0.2.0/node_modules/nprogress/nprogress.js": [],
  "src/modules/nprogress.ts": [],
  "node_modules/.pnpm/vue-demi@0.13.11_vue@3.2.45/node_modules/vue-demi/lib/index.mjs": [],
  "node_modules/.pnpm/pinia@2.0.25_mgnvym7yiazkylwwogi5r767ue/node_modules/pinia/dist/pinia.mjs": [],
  "src/modules/pinia.ts": [],
  "\u0000vite/preload-helper": [],
  "src/modules/pwa.ts": [],
  "node_modules/.pnpm/vue-router@4.1.6_vue@3.2.45/node_modules/vue-router/dist/vue-router.mjs": [],
  "node_modules/.pnpm/hookable@5.4.2/node_modules/hookable/dist/index.mjs": [],
  "node_modules/.pnpm/@unhead+vue@1.0.4_vue@3.2.45/node_modules/@unhead/vue/dist/index.mjs": [],
  "node_modules/.pnpm/@unhead+dom@1.0.4/node_modules/@unhead/dom/dist/index.mjs": [],
  "node_modules/.pnpm/@vueuse+head@1.0.18_vue@3.2.45/node_modules/@vueuse/head/dist/index.mjs": [],
  "node_modules/.pnpm/vite-ssg@0.22.0_btsslyppnm7dvf4lyxme2fuxdq/node_modules/vite-ssg/dist/shared/vite-ssg.a009fbf1.mjs": [],
  "node_modules/.pnpm/vite-ssg@0.22.0_btsslyppnm7dvf4lyxme2fuxdq/node_modules/vite-ssg/dist/shared/vite-ssg.5912142e.mjs": [],
  "node_modules/.pnpm/vite-ssg@0.22.0_btsslyppnm7dvf4lyxme2fuxdq/node_modules/vite-ssg/dist/index.mjs": [],
  "node_modules/.pnpm/@vueuse+shared@9.5.0_vue@3.2.45/node_modules/@vueuse/shared/index.mjs": [],
  "node_modules/.pnpm/@vueuse+core@9.5.0_vue@3.2.45/node_modules/@vueuse/core/index.mjs": [],
  "src/composables/dark.ts": [],
  "src/components/Footer.vue?vue&type=script&setup=true&lang.ts": [],
  "src/layouts/default.vue?vue&type=style&index=0&scoped=d2b10593&lang.css": [],
  "\u0000plugin-vue:export-helper": [],
  "src/layouts/default.vue": [],
  "../../../../../../@vite-plugin-vue-layouts/generated-layouts": [],
  "\u0000virtual:vue-component-preview": [],
  "src/App.vue?vue&type=script&setup=true&lang.ts": [],
  "src/pages/index.vue?vue&type=script&lang.ts": [],
  "src/pages/index.vue?vue&type=style&index=0&scoped=28146513&lang.css": [],
  "src/pages/index.vue": [],
  "../../../../../../@vite-plugin-pages/generated-pages?id=~pages": [],
  "node_modules/.pnpm/@unocss+reset@0.46.5/node_modules/@unocss/reset/tailwind.css": [],
  "src/styles/main.css": [],
  "../../../../../../__uno.css": [],
  "src/main.ts": [],
  "index.html": [],
  "assets/app.1296fd7c.js-unocss-hash.css": [],
  "../../../../../../@vite-plugin-pwa/virtual:pwa-register": [
    "/tyt-ruleset/assets/virtual_pwa-register.52987ca0.js"
  ],
  "src/layouts/404.vue?vue&type=script&setup=true&lang.ts": [
    "/tyt-ruleset/assets/404.d05f9880.js"
  ],
  "src/layouts/404.vue": [
    "/tyt-ruleset/assets/404.d05f9880.js"
  ],
  "src/layouts/home.vue": [
    "/tyt-ruleset/assets/home.59fb6e2a.js"
  ],
  "src/pages/whitehack/toc.md": [
    "/tyt-ruleset/assets/toc.80285588.js"
  ],
  "src/pages/whitehack/tables.md": [
    "/tyt-ruleset/assets/tables.e1df90be.js"
  ],
  "src/pages/whitehack/figures.md": [
    "/tyt-ruleset/assets/figures.0403fe07.js"
  ],
  "src/pages/Tresspasser/toc.md": [
    "/tyt-ruleset/assets/toc.9ed8ca72.js"
  ],
  "src/pages/rules/index.vue?vue&type=script&lang.ts": [
    "/tyt-ruleset/assets/index.2864d9a5.js",
    "/tyt-ruleset/assets/index.0fe82511.css"
  ],
  "src/pages/rules/index.vue?vue&type=style&index=0&scoped=4976d101&lang.css": [
    "/tyt-ruleset/assets/index.2864d9a5.js",
    "/tyt-ruleset/assets/index.0fe82511.css"
  ],
  "src/pages/rules/index.vue": [
    "/tyt-ruleset/assets/index.2864d9a5.js",
    "/tyt-ruleset/assets/index.0fe82511.css"
  ],
  "src/pages/Entromancy/toc.md": [
    "/tyt-ruleset/assets/toc.ddd032c7.js"
  ],
  "src/pages/campaigns/index.vue?vue&type=script&lang.ts": [
    "/tyt-ruleset/assets/index.ff4630c4.js",
    "/tyt-ruleset/assets/index.449e6824.css"
  ],
  "src/pages/campaigns/index.vue?vue&type=style&index=0&scoped=32ad78b4&lang.css": [
    "/tyt-ruleset/assets/index.ff4630c4.js",
    "/tyt-ruleset/assets/index.449e6824.css"
  ],
  "src/pages/campaigns/index.vue": [
    "/tyt-ruleset/assets/index.ff4630c4.js",
    "/tyt-ruleset/assets/index.449e6824.css"
  ],
  "src/pages/README.md": [
    "/tyt-ruleset/assets/README.0cc70881.js"
  ],
  "src/pages/about.md": [
    "/tyt-ruleset/assets/about.9b5ab085.js"
  ],
  "src/pages/[...all].vue?vue&type=script&setup=true&lang.ts": [
    "/tyt-ruleset/assets/_...all_.10057e0f.js"
  ],
  "../../../../../../@vite-plugin-pages/route-block": [
    "/tyt-ruleset/assets/_...all_.10057e0f.js"
  ],
  "src/pages/[...all].vue": [
    "/tyt-ruleset/assets/_...all_.10057e0f.js"
  ],
  "src/store/user.ts": [
    "/tyt-ruleset/assets/_name_.aa229364.js"
  ],
  "src/pages/hi/[name].vue?vue&type=script&setup=true&lang.ts": [
    "/tyt-ruleset/assets/_name_.aa229364.js"
  ],
  "src/pages/hi/[name].vue": [
    "/tyt-ruleset/assets/_name_.aa229364.js"
  ],
  "node_modules/.pnpm/workbox-window@6.5.4/node_modules/workbox-window/build/workbox-window.prod.es5.mjs": [
    "/tyt-ruleset/assets/workbox-window.prod.es5.6954f450.js"
  ]
}